wittiot/__init__.py
wittiot/api.py
wittiot/const.py
wittiot/errors.py
wittiot/t.py
wittiot-1.0.33.dist-info/licenses/LICENSE
wittiot-1.0.33.dist-info/METADATA
wittiot-1.0.33.dist-info/WHEEL
wittiot-1.0.33.dist-info/top_level.txt
wittiot-1.0.33.dist-info/RECORD
